README
setup.py
mysimplecalculator/__init__.py
mysimplecalculator.egg-info/PKG-INFO
mysimplecalculator.egg-info/SOURCES.txt
mysimplecalculator.egg-info/dependency_links.txt
mysimplecalculator.egg-info/top_level.txt