Metadata-Version: 1.1
Name: mysimplecalculator
Version: 0.0.4
Summary: An demonstration of how to create, document, and publish to the cheese shop a5 pypi.org.
Home-page: http://packages.python.org/an_example_pypi_project
Author: mohammed yousuf uddin
Author-email: reach2yousuf@gmail.com
License: BSD
Keywords: example documentation tutorial
Platform: UNKNOWN
Classifier: Development Status :: 3 - Alpha
Classifier: Topic :: Utilities
Classifier: License :: OSI Approved :: BSD License
